[
    {
        "Sl.No": "1",
        "Name of the Student": "Shwetha S",
        "Current Position": "PhD  Scholar",
        "Company/Institution": "IIT Madras",
        "Type": "Academia"
    },
    {
        "Sl.No": "2",
        "Name of the Student": "Pavithra.S",
        "Current Position": "Scientist",
        "Company/Institution": "Aganitha Cognitive Solutions, Hyderabad",
        "Type": "Industry"
    },
    {
        "Sl.No": "3",
        "Name of the Student": "Soumya Ranjan",
        "Current Position": "PhD  Scholar",
        "Company/Institution": "THSTI",
        "Type": "Academia"
    },
    {
        "Sl.No": "4",
        "Name of the Student": "Murali Aaditya Ms",
        "Current Position": "PhD  Scholar",
        "Company/Institution": "IIT Bombay",
        "Type": "Academia"
    },
    {
        "Sl.No": "5",
        "Name of the Student": "Puppala Alekhya",
        "Current Position": "PhD  Scholar",
        "Company/Institution": "The University of Alabama, United States",
        "Type": "Academia"
    },
    {
        "Sl.No": "6",
        "Name of the Student": "Sreenath Dey",
        "Current Position": "JRF",
        "Company/Institution": "TIFR-Hyd",
        "Type": "Academia"
    },
    {
        "Sl.No": "7",
        "Name of the Student": "Bhuvana K",
        "Current Position": "Project Assistant",
        "Company/Institution": "IIT Hyderabad",
        "Type": "Academia"
    },
    {
        "Sl.No": "8",
        "Name of the Student": "Gujjala Anil Vikas",
        "Current Position": "PhD  Scholar",
        "Company/Institution": "Virginia Commonwealth University",
        "Type": "Academia"
    },
    {
        "Sl.No": "9",
        "Name of the Student": "Ayan Das",
        "Current Position": "PhD  Scholar",
        "Company/Institution": "UNSW, Sydney",
        "Type": "Academia"
    }
]